smparts/__init__.py
smparts/reset_buffer.py
smparts/sentinels.py
smparts-0.0.0a1.dist-info/licenses/LICENSE
smparts-0.0.0a1.dist-info/METADATA
smparts-0.0.0a1.dist-info/WHEEL
smparts-0.0.0a1.dist-info/top_level.txt
smparts-0.0.0a1.dist-info/RECORD
