Metadata-Version: 2.4
Name: smparts
Version: 0.0.0a1
Summary: Composable parts for building state machines.
Author-email: Qirui Li <github@qirui.li>
Maintainer-email: Qirui Li <github@qirui.li>
License: MIT License
Project-URL: Homepage, https://github.com/honeymath/smparts
Project-URL: Issues, https://github.com/honeymath/smparts/issues
Project-URL: Source, https://github.com/honeymath/smparts/
Keywords: state-machine,components
Classifier: Development Status :: 3 - Alpha
Classifier: Intended Audience :: Developers
Classifier: Topic :: Software Development :: Libraries
Classifier: License :: OSI Approved :: MIT License
Classifier: Programming Language :: Python :: 3
Classifier: Programming Language :: Python :: 3.9
Classifier: Programming Language :: Python :: 3.10
Classifier: Programming Language :: Python :: 3.11
Classifier: Programming Language :: Python :: 3.12
Classifier: Programming Language :: Python :: 3.13
Classifier: Programming Language :: Python :: 3 :: Only
Requires-Python: >=3.9
License-File: LICENSE
Provides-Extra: dev
Requires-Dist: pytest; extra == "dev"
Requires-Dist: ruff; extra == "dev"
Provides-Extra: test
Requires-Dist: pytest; extra == "test"
Requires-Dist: coverage; extra == "test"
Dynamic: license-file
